vscphelper.py
pyvscphelper-0.0.12.data/data/my_data/data_file
sample/__init__.py
sample/package_data.dat
pyvscphelper-0.0.12.dist-info/LICENSE
pyvscphelper-0.0.12.dist-info/METADATA
pyvscphelper-0.0.12.dist-info/WHEEL
pyvscphelper-0.0.12.dist-info/entry_points.txt
pyvscphelper-0.0.12.dist-info/top_level.txt
pyvscphelper-0.0.12.dist-info/RECORD
